{
  "$schema": "https://schema.management.azure.com/schemas/2019-04-01/deploymentTemplate.json#",
  "contentVersion": "1.0.0.0",
  "metadata": {
    "_generator": {
      "name": "bicep",
      "version": "0.39.26.7824",
      "templateHash": "11793498243009164131"
    }
  },
  "parameters": {
    "environmentName": {
      "type": "string",
      "minLength": 1,
      "maxLength": 64,
      "metadata": {
        "description": "Name of the environment that will be used for resource naming"
      }
    },
    "location": {
      "type": "string",
      "minLength": 1,
      "metadata": {
        "description": "Primary location for all resources"
      }
    },
    "principalId": {
      "type": "string",
      "defaultValue": "",
      "metadata": {
        "description": "Id of the principal to assign database and application roles"
      }
    }
  },
  "variables": {
    "resourceToken": "[uniqueString(subscription().id, resourceGroup().id, parameters('location'), parameters('environmentName'))]",
    "tags": {
      "azd-env-name": "[parameters('environmentName')]"
    }
  },
  "resources": [
    {
      "type": "Microsoft.ManagedIdentity/userAssignedIdentities",
      "apiVersion": "2023-01-31",
      "name": "[format('azmi{0}', variables('resourceToken'))]",
      "location": "[parameters('location')]",
      "tags": "[variables('tags')]"
    },
    {
      "type": "Microsoft.OperationalInsights/workspaces",
      "apiVersion": "2022-10-01",
      "name": "[format('azlog{0}', variables('resourceToken'))]",
      "location": "[parameters('location')]",
      "tags": "[variables('tags')]",
      "properties": {
        "sku": {
          "name": "PerGB2018"
        },
        "retentionInDays": 30
      }
    },
    {
      "type": "Microsoft.Insights/components",
      "apiVersion": "2020-02-02",
      "name": "[format('azai{0}', variables('resourceToken'))]",
      "location": "[parameters('location')]",
      "tags": "[variables('tags')]",
      "kind": "web",
      "properties": {
        "Application_Type": "web",
        "WorkspaceResourceId": "[resourceId('Microsoft.OperationalInsights/workspaces', format('azlog{0}', variables('resourceToken')))]"
      },
      "dependsOn": [
        "[resourceId('Microsoft.OperationalInsights/workspaces', format('azlog{0}', variables('resourceToken')))]"
      ]
    },
    {
      "type": "Microsoft.ContainerRegistry/registries",
      "apiVersion": "2023-07-01",
      "name": "[format('azacr{0}', variables('resourceToken'))]",
      "location": "[parameters('location')]",
      "tags": "[variables('tags')]",
      "sku": {
        "name": "Basic"
      },
      "properties": {
        "adminUserEnabled": false,
        "publicNetworkAccess": "Enabled"
      }
    },
    {
      "type": "Microsoft.Authorization/roleAssignments",
      "apiVersion": "2022-04-01",
      "scope": "[format('Microsoft.ContainerRegistry/registries/{0}', format('azacr{0}', variables('resourceToken')))]",
      "name": "[guid(resourceId('Microsoft.ContainerRegistry/registries', format('azacr{0}', variables('resourceToken'))), resourceId('Microsoft.ManagedIdentity/userAssignedIdentities', format('azmi{0}', variables('resourceToken'))), 'acrPull')]",
      "properties": {
        "principalId": "[reference(resourceId('Microsoft.ManagedIdentity/userAssignedIdentities', format('azmi{0}', variables('resourceToken'))), '2023-01-31').principalId]",
        "roleDefinitionId": "[subscriptionResourceId('Microsoft.Authorization/roleDefinitions', '7f951dda-4ed3-4680-a7ca-43fe172d538d')]",
        "principalType": "ServicePrincipal"
      },
      "dependsOn": [
        "[resourceId('Microsoft.ContainerRegistry/registries', format('azacr{0}', variables('resourceToken')))]",
        "[resourceId('Microsoft.ManagedIdentity/userAssignedIdentities', format('azmi{0}', variables('resourceToken')))]"
      ]
    },
    {
      "type": "Microsoft.KeyVault/vaults",
      "apiVersion": "2023-07-01",
      "name": "[format('azkv{0}', variables('resourceToken'))]",
      "location": "[parameters('location')]",
      "tags": "[variables('tags')]",
      "properties": {
        "sku": {
          "family": "A",
          "name": "standard"
        },
        "tenantId": "[subscription().tenantId]",
        "enableRbacAuthorization": true,
        "publicNetworkAccess": "Enabled",
        "networkAcls": {
          "defaultAction": "Allow",
          "bypass": "AzureServices"
        }
      }
    },
    {
      "type": "Microsoft.Authorization/roleAssignments",
      "apiVersion": "2022-04-01",
      "scope": "[format('Microsoft.KeyVault/vaults/{0}', format('azkv{0}', variables('resourceToken')))]",
      "name": "[guid(resourceId('Microsoft.KeyVault/vaults', format('azkv{0}', variables('resourceToken'))), resourceId('Microsoft.ManagedIdentity/userAssignedIdentities', format('azmi{0}', variables('resourceToken'))), 'secretsOfficer')]",
      "properties": {
        "principalId": "[reference(resourceId('Microsoft.ManagedIdentity/userAssignedIdentities', format('azmi{0}', variables('resourceToken'))), '2023-01-31').principalId]",
        "roleDefinitionId": "[subscriptionResourceId('Microsoft.Authorization/roleDefinitions', 'b86a8fe4-44ce-4948-aee5-eccb2c155cd7')]",
        "principalType": "ServicePrincipal"
      },
      "dependsOn": [
        "[resourceId('Microsoft.KeyVault/vaults', format('azkv{0}', variables('resourceToken')))]",
        "[resourceId('Microsoft.ManagedIdentity/userAssignedIdentities', format('azmi{0}', variables('resourceToken')))]"
      ]
    },
    {
      "type": "Microsoft.App/managedEnvironments",
      "apiVersion": "2024-03-01",
      "name": "[format('azcae{0}', variables('resourceToken'))]",
      "location": "[parameters('location')]",
      "tags": "[variables('tags')]",
      "properties": {
        "appLogsConfiguration": {
          "destination": "log-analytics",
          "logAnalyticsConfiguration": {
            "customerId": "[reference(resourceId('Microsoft.OperationalInsights/workspaces', format('azlog{0}', variables('resourceToken'))), '2022-10-01').customerId]",
            "sharedKey": "[listKeys(resourceId('Microsoft.OperationalInsights/workspaces', format('azlog{0}', variables('resourceToken'))), '2022-10-01').primarySharedKey]"
          }
        }
      },
      "dependsOn": [
        "[resourceId('Microsoft.OperationalInsights/workspaces', format('azlog{0}', variables('resourceToken')))]"
      ]
    },
    {
      "type": "Microsoft.App/containerApps",
      "apiVersion": "2024-03-01",
      "name": "[format('azca{0}', variables('resourceToken'))]",
      "location": "[parameters('location')]",
      "tags": "[union(variables('tags'), createObject('azd-service-name', 'petclinic'))]",
      "identity": {
        "type": "UserAssigned",
        "userAssignedIdentities": {
          "[format('{0}', resourceId('Microsoft.ManagedIdentity/userAssignedIdentities', format('azmi{0}', variables('resourceToken'))))]": {}
        }
      },
      "properties": {
        "environmentId": "[resourceId('Microsoft.App/managedEnvironments', format('azcae{0}', variables('resourceToken')))]",
        "configuration": {
          "ingress": {
            "external": true,
            "targetPort": 8080,
            "transport": "auto",
            "corsPolicy": {
              "allowedOrigins": [
                "*"
              ],
              "allowedMethods": [
                "*"
              ],
              "allowedHeaders": [
                "*"
              ]
            }
          },
          "registries": [
            {
              "server": "[reference(resourceId('Microsoft.ContainerRegistry/registries', format('azacr{0}', variables('resourceToken'))), '2023-07-01').loginServer]",
              "identity": "[resourceId('Microsoft.ManagedIdentity/userAssignedIdentities', format('azmi{0}', variables('resourceToken')))]"
            }
          ]
        },
        "template": {
          "containers": [
            {
              "name": "petclinic",
              "image": "mcr.microsoft.com/azuredocs/containerapps-helloworld:latest",
              "resources": {
                "cpu": "[json('0.5')]",
                "memory": "1Gi"
              },
              "env": [
                {
                  "name": "APPLICATIONINSIGHTS_CONNECTION_STRING",
                  "value": "[reference(resourceId('Microsoft.Insights/components', format('azai{0}', variables('resourceToken'))), '2020-02-02').ConnectionString]"
                },
                {
                  "name": "SPRING_PROFILES_ACTIVE",
                  "value": "default"
                },
                {
                  "name": "SERVER_PORT",
                  "value": "8080"
                }
              ]
            }
          ],
          "scale": {
            "minReplicas": 1,
            "maxReplicas": 10
          }
        }
      },
      "dependsOn": [
        "[extensionResourceId(resourceId('Microsoft.ContainerRegistry/registries', format('azacr{0}', variables('resourceToken'))), 'Microsoft.Authorization/roleAssignments', guid(resourceId('Microsoft.ContainerRegistry/registries', format('azacr{0}', variables('resourceToken'))), resourceId('Microsoft.ManagedIdentity/userAssignedIdentities', format('azmi{0}', variables('resourceToken'))), 'acrPull'))]",
        "[resourceId('Microsoft.Insights/components', format('azai{0}', variables('resourceToken')))]",
        "[resourceId('Microsoft.App/managedEnvironments', format('azcae{0}', variables('resourceToken')))]",
        "[resourceId('Microsoft.ContainerRegistry/registries', format('azacr{0}', variables('resourceToken')))]",
        "[extensionResourceId(resourceId('Microsoft.KeyVault/vaults', format('azkv{0}', variables('resourceToken'))), 'Microsoft.Authorization/roleAssignments', guid(resourceId('Microsoft.KeyVault/vaults', format('azkv{0}', variables('resourceToken'))), resourceId('Microsoft.ManagedIdentity/userAssignedIdentities', format('azmi{0}', variables('resourceToken'))), 'secretsOfficer'))]",
        "[resourceId('Microsoft.ManagedIdentity/userAssignedIdentities', format('azmi{0}', variables('resourceToken')))]"
      ]
    }
  ],
  "outputs": {
    "AZURE_CONTAINER_REGISTRY_ENDPOINT": {
      "type": "string",
      "value": "[reference(resourceId('Microsoft.ContainerRegistry/registries', format('azacr{0}', variables('resourceToken'))), '2023-07-01').loginServer]"
    },
    "AZURE_CONTAINER_REGISTRY_NAME": {
      "type": "string",
      "value": "[format('azacr{0}', variables('resourceToken'))]"
    },
    "AZURE_KEY_VAULT_NAME": {
      "type": "string",
      "value": "[format('azkv{0}', variables('resourceToken'))]"
    },
    "AZURE_KEY_VAULT_ENDPOINT": {
      "type": "string",
      "value": "[reference(resourceId('Microsoft.KeyVault/vaults', format('azkv{0}', variables('resourceToken'))), '2023-07-01').vaultUri]"
    },
    "APPLICATIONINSIGHTS_CONNECTION_STRING": {
      "type": "string",
      "value": "[reference(resourceId('Microsoft.Insights/components', format('azai{0}', variables('resourceToken'))), '2020-02-02').ConnectionString]"
    },
    "PETCLINIC_URL": {
      "type": "string",
      "value": "[format('https://{0}', reference(resourceId('Microsoft.App/containerApps', format('azca{0}', variables('resourceToken'))), '2024-03-01').configuration.ingress.fqdn)]"
    },
    "RESOURCE_GROUP_ID": {
      "type": "string",
      "value": "[resourceGroup().id]"
    }
  }
}